README.rst
setup.py
digitemp/__init__.py
digitemp/exceptions.py
digitemp/master.py
digitemp/utils.py
digitemp/device/__init__.py
digitemp/device/factories.py
digitemp/device/generic.py
digitemp/device/thermometer.py
digitemp/test/__init__.py
digitemp/test/test_utils.py
digitemp/test/device/__init__.py
digitemp/test/device/test_thermometer.py
pydigitemp.egg-info/PKG-INFO
pydigitemp.egg-info/SOURCES.txt
pydigitemp.egg-info/dependency_links.txt
pydigitemp.egg-info/requires.txt
pydigitemp.egg-info/top_level.txt